tests/__init__.py
tests/test_exception_job.py
tests/test_parallelization.py
tests/test_queue_filling.py
timeoutpool/__init__.py
timeoutpool/_parallelization.py
timeoutpool/_version.py
timeoutpool-0.1.1.dist-info/LICENSE
timeoutpool-0.1.1.dist-info/METADATA
timeoutpool-0.1.1.dist-info/WHEEL
timeoutpool-0.1.1.dist-info/top_level.txt
timeoutpool-0.1.1.dist-info/RECORD
