Metadata-Version: 2.1
Name: timeoutpool
Version: 0.1.1
Summary: Process pool with timeout for each individual job.
Home-page: https://github.com/gykovacs/timeoutpool
Download-URL: https://github.com/gykovacs/timeoutpool
Author: Gyorgy Kovacs
Author-email: gyuriofkovacs@gmail.com
Maintainer: Gyorgy Kovacs
Maintainer-email: gyuriofkovacs@gmail.com
License: MIT
Classifier: Intended Audience :: Science/Research
Classifier: Intended Audience :: Developers
Classifier: Development Status :: 3 - Alpha
Classifier: License :: OSI Approved :: MIT License
Classifier: Programming Language :: Python
Classifier: Topic :: Scientific/Engineering :: Artificial Intelligence
Classifier: Topic :: Software Development
Classifier: Operating System :: Microsoft :: Windows
Classifier: Operating System :: POSIX
Classifier: Operating System :: Unix
Classifier: Operating System :: MacOS
Requires-Python: >=3.5
Provides-Extra: tests
Provides-Extra: docs
License-File: LICENSE
